ljtest/__init__.py
ljtest/sampleCode.py
ljtest-0.2.0.dist-info/METADATA
ljtest-0.2.0.dist-info/WHEEL
ljtest-0.2.0.dist-info/top_level.txt
ljtest-0.2.0.dist-info/RECORD
