Metadata-Version: 2.1
Name: ljtest
Version: 0.2.0
Summary: uploading python package
Home-page: UNKNOWN
Author: Lee Jung
Author-email: lj8763@naver.com
License: UNKNOWN
Keywords: pypi
Platform: UNKNOWN
Classifier: Programming Language :: Python :: 3
Classifier: Programming Language :: Python :: 3.2
Classifier: Programming Language :: Python :: 3.3
Classifier: Programming Language :: Python :: 3.4
Classifier: Programming Language :: Python :: 3.5
Classifier: Programming Language :: Python :: 3.6
Classifier: Programming Language :: Python :: 3.7
Requires-Python: >=3
